flibbyno/__init__.py
flibbyno/main.py
flibbyno-0.0.1.dist-info/licenses/LICENSE
flibbyno-0.0.1.dist-info/METADATA
flibbyno-0.0.1.dist-info/WHEEL
flibbyno-0.0.1.dist-info/top_level.txt
flibbyno-0.0.1.dist-info/RECORD
