Metadata-Version: 2.4
Name: flibbyno
Version: 0.0.1
Summary: A small example package
Home-page: https://ornicho.la/flibbyno
Author: ornichola
Author-email: ornichola <ornichola@gmail.com>
License-Expression: MIT
Project-URL: Homepage, https://github.com/pypa/sampleproject
Project-URL: Issues, https://github.com/pypa/sampleproject/issues
Classifier: Programming Language :: Python :: 3
Classifier: Operating System :: OS Independent
Requires-Python: >=3.13
License-File: LICENSE
Dynamic: author
Dynamic: home-page
Dynamic: license-file
Dynamic: requires-python
